README.md
setup.cfg
setup.py
oembedders/__init__.py
oembedders.egg-info/PKG-INFO
oembedders.egg-info/SOURCES.txt
oembedders.egg-info/dependency_links.txt
oembedders.egg-info/entry_points.txt
oembedders.egg-info/requires.txt
oembedders.egg-info/top_level.txt
oembedders/providers/23hq.yml
oembedders/providers/GIPHY.yml
oembedders/providers/Infoveave.yml
oembedders/providers/Injurymap.yml
oembedders/providers/adways.yml
oembedders/providers/alpha_app_net.yml
oembedders/providers/altrulabs.yml
oembedders/providers/amcharts_live_editor.yml
oembedders/providers/animatron.yml
oembedders/providers/animoto.yml
oembedders/providers/audiomack.yml
oembedders/providers/audiosnaps.yml
oembedders/providers/backtracks.yml
oembedders/providers/bal.yml
oembedders/providers/beautiful.yml
oembedders/providers/blackfire.io.yml
oembedders/providers/boxofficebuz.yml
oembedders/providers/briovr.yml
oembedders/providers/buttondown.yml
oembedders/providers/cacoo.yml
oembedders/providers/carbonhealth.yml
oembedders/providers/catboat.yml
oembedders/providers/ceros.yml
oembedders/providers/chartblocks.yml
oembedders/providers/chirbit.com.yml
oembedders/providers/circuitlab.yml
oembedders/providers/clipland.yml
oembedders/providers/clyp.yml
oembedders/providers/codehs.yml
oembedders/providers/codepen.yml
oembedders/providers/codepoints.yml
oembedders/providers/codesandbox.yml
oembedders/providers/collegehumor.yml
oembedders/providers/commaful.yml
oembedders/providers/coub.yml
oembedders/providers/crowd_ranking.yml
oembedders/providers/cyrano.yml
oembedders/providers/daily_mile.yml
oembedders/providers/dailymotion.yml
oembedders/providers/deseretnews.yml
oembedders/providers/deviantart.com.yml
oembedders/providers/didacte.yml
oembedders/providers/digiteka.yml
oembedders/providers/dipity.yml
oembedders/providers/docdroid.yml
oembedders/providers/dotsub.yml
oembedders/providers/dtube.yml
oembedders/providers/edocr.yml
oembedders/providers/edumedia-sciences.com.yml
oembedders/providers/egliseinfo.yml
oembedders/providers/embed_articles.yml
oembedders/providers/embedly.yml
oembedders/providers/ethfiddle.yml
oembedders/providers/eyrieio.yml
oembedders/providers/facebook-post.yml
