Metadata-Version: 2.1
Name: oembedders
Version: 0.0.3
Summary: A utility for dispatching to known oembed providers
Home-page: https://github.com/oembedders
Author: Ed Summers
Author-email: ehs@pobox.com
License: UNKNOWN
Platform: UNKNOWN
Requires-Python: >=3
